Metadata-Version: 2.1
Name: django-check-migration-wtf
Version: 1.4.0
Summary: A line of description
Home-page: https://github.com/antonioIrizar/django-check-migration-wtf
Author: Antonio Irizar
Author-email: antonioirizar@gmail.com
License: GLP3
Keywords: django postgres postgresql migrations
Platform: UNKNOWN
Classifier: Development Status :: 5 - Production/Stable
Classifier: Intended Audience :: Developers
Classifier: Operating System :: OS Independent
Classifier: License :: OSI Approved :: GNU General Public License v3 (GPLv3)
Classifier: Programming Language :: Python
Classifier: Programming Language :: Python :: 3.7
Classifier: Programming Language :: Python :: 3.8
Classifier: Programming Language :: Python :: 3.9
Classifier: Programming Language :: Python :: 3.10
Classifier: Programming Language :: Python :: 3.11
Classifier: Framework :: Django
Classifier: Framework :: Django :: 2.2
Classifier: Framework :: Django :: 3.0
Classifier: Framework :: Django :: 3.1
Classifier: Framework :: Django :: 3.2
Classifier: Framework :: Django :: 4.0
Classifier: Framework :: Django :: 4.1
Requires-Python: >=3.7
Requires-Dist: Django (<4.2,>=2.2)
Requires-Dist: PyGithub (<2,>=1.50)
